{
  "type": "minecraft:crafting_shaped",
  "pattern": [
    "ABC",
    "DEF",
    " H "
  ],
  "key": {
    "A": {
      "item": "croptopia:butter"
    },
    "B": {
      "tag": "c:cbc_garlic"
    },
    "C": {
      "tag": "c:cbc_salt"
    },
    "D": {
      "item": "croptopia:pepper"
    },
    "E": {
      "item": "croptopia:crab"
    },
    "F": {
      "item": "croptopia:crab"
    },
    "H": {
      "item": "croptopia:frying_pan"
    }
  },
  "result": {
    "item": "croptopia:crab_legs",
    "count": 2
  }
}